Workbook

Sheet Read Me
A1: Personal Investment Portfolio Tracker
A2: This project is an Excel-based portfolio management and financial analysis tool that helps track investment transactions, calculate current holdings and portfolio value, analyze unrealized profit/loss and returns, and visualize portfolio allocation through an interactive dashboard.
A4: Purpose:
A5: An Excel-based tool for tracking investment transactions, holdings, portfolio value, unrealized P/L, returns and portfolio allocation.
A7: Tools Used: Microsoft Excel Key Excel Functions: - SUM - SUMIFS - IFERROR - COUNTA
A9: Features: - Transaction tracking - Portfolio holdings calculation - Current portfolio valuation - Profit/loss analysis - Return calculation - Portfolio allocation - Dashboard visualization
A11: Project Outcome:
A12: The completed tracker provides a consolidated view of portfolio holdings, investment value, unrealized profit/loss, returns and portfolio allocation through an Excel dashboard.
A14: Limitations: - Current market prices are manually entered. - This beginner version does not calculate realized P/L or taxes. - Historical market-price data is not automatically imported.
A16: Future Improvements: - Automatic market-price updates - Python integration - Risk analysis - Sharpe ratio - Portfolio volatility - Web dashboard
A19: Data Note: Sample transactions and market prices used in this project are illustrative and are intended to demonstrate portfolio tracking and financial analysis functionality.

Sheet Dashboard
A1: PERSONAL INVESTMENT PORTFOLIO TRACKER
A2: Excel-Based Financial Analysis Dashboard
A3: Total Invested
A4: =Analysis!B2 -> 32980
A5: Current Portfolio Value
A6: =Analysis!B3 -> 34120
A7: Total Unrealized P/L
A8: ='Holdings '!I6 -> 1140
A9: Overall Return
A10: =A8/A4 -> 0.034566404
A13: Stock | B13: Current Value | D13: Stock | E13: Unrealized P/L | G13: Metric | H13: Amount
A14: ='Holdings '!A2 -> Reliance Industries | B14: ='Holdings '!H2 -> 7250 | D14: ='Holdings '!A2 -> Reliance Industries | E14: ='Holdings '!I2 -> 230 | G14: =Analysis!A2 -> Total Invested | H14: =Analysis!B2 -> 32980
A15: ='Holdings '!A3 -> HDFC Bank | B15: ='Holdings '!H3 -> 7760 | D15: ='Holdings '!A3 -> HDFC Bank | E15: ='Holdings '!I3 -> 140 | G15: =Analysis!A3 -> Current Portfolio Value | H15: =Analysis!B3 -> 34120
A16: ='Holdings '!A4 -> TCS | B16: ='Holdings '!H4 -> 9750 | D16: ='Holdings '!A4 -> TCS | E16: ='Holdings '!I4 -> 430
A17: ='Holdings '!A5 -> Infosys | B17: ='Holdings '!H5 -> 9360 | D17: ='Holdings '!A5 -> Infosys | E17: ='Holdings '!I5 -> 340

Sheet Transactions 
A1: Date | B1: Stock Name | C1: Symbol | D1: Transaction Type | E1: Quantity | F1: Price per Share | G1: Brokerage | H1: Total Amount
A2: 46270 | B2: Reliance Industries | C2: RELIANCE | D2: Buy | E2: 5 | F2: 1400 | G2: 20 | H2: =E2*F2+G2 -> 7020
A3: 46271 | B3: HDFC Bank | C3: HDFCBANK | D3: Buy | E3: 8 | F3: 950 | G3: 20 | H3: =E3*F3+G3 -> 7620
A4: 46272 | B4: TCS | C4: TCS | D4: Buy | E4: 3 | F4: 3100 | G4: 20 | H4: =E4*F4+G4 -> 9320
A5: 46273 | B5: Infosys | C5: INFY | D5: Buy | E5: 6 | F5: 1500 | G5: 20 | H5: =E5*F5+G5 -> 9020

Sheet Holdings 
A1: Stock Name | B1: Symbol | C1: Quantity | D1: Average Buy Price | E1: Brokerage | F1: Total Invested | G1: Current Price | H1: Current Value | I1: Unrealized P/L | J1: Return % | K1: Portfolio Weight
A2: Reliance Industries | B2: RELIANCE | C2: =SUMIFS(TransactionsTable[Quantity],TransactionsTable[Symbol],B2,TransactionsTable[Transaction Type],"Buy")-SUMIFS(TransactionsTable[Quantity],TransactionsTable[Symbol],B2,TransactionsTable[Transaction Type],"Sell") -> 5 | D2: 1400 | E2: =SUMIFS(TransactionsTable[Brokerage],TransactionsTable[Symbol],B2,TransactionsTable[Transaction Type],"Buy") -> 20 | F2: =C2*D2+E2 -> 7020 | G2: 1450 | H2: =C2*G2 -> 7250 | I2: =H2-F2 -> 230 | J2: =IFERROR(I2/F2,0) -> 0.032763533 | K2: =IFERROR(H2/SUM($H$2:$H$5),0) -> 0.21248535
A3: HDFC Bank | B3: HDFCBANK | C3: =SUMIFS(TransactionsTable[Quantity],TransactionsTable[Symbol],B3,TransactionsTable[Transaction Type],"Buy")-SUMIFS(TransactionsTable[Quantity],TransactionsTable[Symbol],B3,TransactionsTable[Transaction Type],"Sell") -> 8 | D3: 950 | E3: =SUMIFS(TransactionsTable[Brokerage],TransactionsTable[Symbol],B3,TransactionsTable[Transaction Type],"Buy") -> 20 | F3: =C3*D3+E3 -> 7620 | G3: 970 | H3: =C3*G3 -> 7760 | I3: =H3-F3 -> 140 | J3: =IFERROR(I3/F3,0) -> 0.018372703 | K3: =IFERROR(H3/SUM($H$2:$H$5),0) -> 0.22743259
A4: TCS | B4: TCS | C4: =SUMIFS(TransactionsTable[Quantity],TransactionsTable[Symbol],B4,TransactionsTable[Transaction Type],"Buy")-SUMIFS(TransactionsTable[Quantity],TransactionsTable[Symbol],B4,TransactionsTable[Transaction Type],"Sell") -> 3 | D4: 3100 | E4: =SUMIFS(TransactionsTable[Brokerage],TransactionsTable[Symbol],B4,TransactionsTable[Transaction Type],"Buy") -> 20 | F4: =C4*D4+E4 -> 9320 | G4: 3250 | H4: =C4*G4 -> 9750 | I4: =H4-F4 -> 430 | J4: =IFERROR(I4/F4,0) -> 0.046137339 | K4: =IFERROR(H4/SUM($H$2:$H$5),0) -> 0.28575615
A5: Infosys | B5: INFY | C5: =SUMIFS(TransactionsTable[Quantity],TransactionsTable[Symbol],B5,TransactionsTable[Transaction Type],"Buy")-SUMIFS(TransactionsTable[Quantity],TransactionsTable[Symbol],B5,TransactionsTable[Transaction Type],"Sell") -> 6 | D5: 1500 | E5: =SUMIFS(TransactionsTable[Brokerage],TransactionsTable[Symbol],B5,TransactionsTable[Transaction Type],"Buy") -> 20 | F5: =C5*D5+E5 -> 9020 | G5: 1560 | H5: =C5*G5 -> 9360 | I5: =H5-F5 -> 340 | J5: =IFERROR(I5/F5,0) -> 0.037694013 | K5: =IFERROR(H5/SUM($H$2:$H$5),0) -> 0.27432591
I6: =SUM(I2:I5) -> 1140

Sheet Analysis
A1: Metric | B1: Value
A2: Total Invested | B2: =SUM('Holdings '!F2:F50) -> 32980
A3: Current Portfolio Value | B3: =SUM('Holdings '!H2:H50) -> 34120
A4: Total Unrealized P/L | B4: =SUM('Holdings '!I2:I5) -> 1140
A5: Overall Return | B5: =IFERROR(B4/B2,0) -> 0.034566404
A6: Number of Holdings | B6: =COUNTA('Holdings '!B2:B5) -> 4
A7: Largest Holding | B7: TCS
A8: Best Performer | B8: TCS
A9: Worst Performer | B9: HDFC Bank
